{
  "planning": [
    {
      "id": 1781508558161,
      "nom": "TCC0015 (Phase Mobile)",
      "technicien": "Fabien VARY",
      "date": "2026-06-17",
      "priorite": "normale",
      "statut": "planifie",
      "note": ""
    },
    {
      "id": 1781510120638.0925,
      "nom": "TCC0015",
      "echantillonCode": "9960000-A",
      "date": "2026-06-15",
      "priorite": "normale",
      "statut": "planifie",
      "note": "Auto: 9960000-A | PIF"
    },
    {
      "id": 1781510120638.6848,
      "nom": "pH",
      "echantillonCode": "9960000-A",
      "date": "2026-06-15",
      "priorite": "normale",
      "statut": "planifie",
      "note": "Auto: 9960000-A | PIF"
    },
    {
      "id": 1781511540450.0483,
      "nom": "TCC0015",
      "echantillonCode": "9960001-A",
      "date": "2026-06-15",
      "priorite": "normale",
      "statut": "planifie",
      "note": "Auto: 9960001-A | PIF STAB"
    },
    {
      "id": 1781511540450.426,
      "nom": "pH",
      "echantillonCode": "9960001-A",
      "date": "2026-06-15",
      "priorite": "normale",
      "statut": "planifie",
      "note": "Auto: 9960001-A | PIF STAB"
    },
    {
      "id": 1781512857183.959,
      "nom": "pH",
      "echantillonCode": "9960002-A",
      "date": "2026-06-15",
      "priorite": "normale",
      "statut": "planifie",
      "note": "Auto: 9960002-A |  STAB"
    },
    {
      "id": 1781602519100.9797,
      "nom": "TCC0015",
      "echantillonCode": "9960003-A",
      "date": "2026-06-16",
      "priorite": "normale",
      "statut": "planifie",
      "note": "Auto: 9960003-A | PIF STAB"
    },
    {
      "id": 1781602519100.2793,
      "nom": "pH",
      "echantillonCode": "9960003-A",
      "date": "2026-06-16",
      "priorite": "normale",
      "statut": "planifie",
      "note": "Auto: 9960003-A | PIF STAB"
    },
    {
      "id": 1781602519100.424,
      "nom": "TCC0015",
      "echantillonCode": "9960003-B",
      "date": "2026-06-16",
      "priorite": "normale",
      "statut": "planifie",
      "note": "Auto: 9960003-B | PIF STAB"
    },
    {
      "id": 1781602519100.862,
      "nom": "pH",
      "echantillonCode": "9960003-B",
      "date": "2026-06-16",
      "priorite": "normale",
      "statut": "planifie",
      "note": "Auto: 9960003-B | PIF STAB"
    },
    {
      "id": 1781602519100.8645,
      "nom": "TCC0015",
      "echantillonCode": "9960003-C",
      "date": "2026-06-16",
      "priorite": "normale",
      "statut": "planifie",
      "note": "Auto: 9960003-C | PIF STAB"
    },
    {
      "id": 1781602519100.941,
      "nom": "pH",
      "echantillonCode": "9960003-C",
      "date": "2026-06-16",
      "priorite": "normale",
      "statut": "planifie",
      "note": "Auto: 9960003-C | PIF STAB"
    },
    {
      "id": 1781853049925.839,
      "nom": "L*a*b",
      "echantillonCode": "AAAAAAA-A",
      "date": "2026-06-19",
      "priorite": "normale",
      "statut": "planifie",
      "note": "Auto: AAAAAAA-A | PIF"
    },
    {
      "id": 1781853049925.3877,
      "nom": "TCC0044",
      "echantillonCode": "AAAAAAA-A",
      "date": "2026-06-19",
      "priorite": "normale",
      "statut": "planifie",
      "note": "Auto: AAAAAAA-A | PIF"
    },
    {
      "id": 1781853049925.9827,
      "nom": "Osmolalité",
      "echantillonCode": "AAAAAAA-A",
      "date": "2026-06-19",
      "priorite": "normale",
      "statut": "planifie",
      "note": "Auto: AAAAAAA-A | PIF"
    },
    {
      "id": 1781960722999.4263,
      "nom": "pH",
      "echantillonCode": "BBBBBB-A",
      "date": "2026-06-20",
      "priorite": "normale",
      "statut": "planifie",
      "note": "Auto: BBBBBB-A | PIF"
    },
    {
      "id": 1781960722999.4268,
      "nom": "L*a*b",
      "echantillonCode": "BBBBBB-A",
      "date": "2026-06-20",
      "priorite": "normale",
      "statut": "planifie",
      "note": "Auto: BBBBBB-A | PIF"
    },
    {
      "id": 1781960722999.6396,
      "nom": "TCC0044",
      "echantillonCode": "BBBBBB-A",
      "date": "2026-06-20",
      "priorite": "normale",
      "statut": "planifie",
      "note": "Auto: BBBBBB-A | PIF"
    },
    {
      "id": 1781960722999.1575,
      "nom": "Osmolalité",
      "echantillonCode": "BBBBBB-A",
      "date": "2026-06-20",
      "priorite": "normale",
      "statut": "planifie",
      "note": "Auto: BBBBBB-A | PIF"
    },
    {
      "id": 1781960722999.5657,
      "nom": "TCC0065",
      "echantillonCode": "BBBBBB-A",
      "date": "2026-06-20",
      "priorite": "normale",
      "statut": "planifie",
      "note": "Auto: BBBBBB-A | PIF"
    },
    {
      "id": 1781960722999.7368,
      "nom": "Volume Extractible",
      "echantillonCode": "BBBBBB-A",
      "date": "2026-06-20",
      "priorite": "normale",
      "statut": "planifie",
      "note": "Auto: BBBBBB-A | PIF"
    }
  ],
  "catalogue": [
    {
      "id": 1781448902884,
      "nom": "TCC0015 (Phase Mobile)",
      "habilitations": [
        "Volume",
        "pH"
      ],
      "duree": "",
      "code": "TCC0015-PM",
      "description": "Préparation de la Phase Mobile selon TCC0015"
    },
    {
      "id": 1781508652926,
      "nom": "TCC0015",
      "habilitations": [
        "HPLC",
        "Volume"
      ],
      "duree": "6h",
      "code": "TCC0015",
      "description": "Dosage Lidocaïne / PHBM / Naphazoline / Impuretés selon TCC0015"
    },
    {
      "id": 1781509335357,
      "nom": "pH",
      "habilitations": [
        "pH"
      ],
      "duree": "",
      "code": "",
      "description": ""
    },
    {
      "id": 1781852405020,
      "nom": "L*a*b",
      "habilitations": [
        "UV"
      ],
      "duree": "",
      "code": "",
      "description": ""
    },
    {
      "id": 1781852438719,
      "nom": "TCC0044",
      "habilitations": [
        "HPLC",
        "Balance",
        "Volume"
      ],
      "duree": "",
      "code": "",
      "description": "Dosage du RM493, des conservateurs et des impuretés"
    },
    {
      "id": 1781852984224,
      "nom": "Osmolalité",
      "habilitations": [
        "Osmolalité"
      ],
      "duree": "",
      "code": "OSMO",
      "description": ""
    },
    {
      "id": 1781959632897,
      "nom": "TCC0065",
      "habilitations": [],
      "duree": "",
      "code": "",
      "description": "Dosage du MPEG"
    },
    {
      "id": 1781959743113,
      "nom": "Volume Extractible",
      "habilitations": [],
      "duree": "",
      "code": "",
      "description": ""
    }
  ],
  "stabilites": [],
  "reactifs": [],
  "produits": [
    {
      "id": 1781446866469,
      "nom": "Méthanol HPLC Grade",
      "fournisseur": "CARLO ERBA",
      "ref": "41239000",
      "localisation": "I4",
      "fc": "0.6",
      "conditionnement": "2.5 L",
      "stockMin": "15",
      "qteCmde": "20",
      "note": ""
    }
  ],
  "contenants": [
    {
      "produitId": 1781446866469,
      "lot": "VBCN32443",
      "qte": "2.5 L",
      "reception": "2026-06-14",
      "peremption": "2028-06-14",
      "ouverture": "2026-06-15",
      "validite": "2027-08-27",
      "statut": "ouvert",
      "note": "",
      "id": 1781449960248
    },
    {
      "produitId": 1781446866469,
      "lot": "VBCN32443",
      "qte": "2.5 L",
      "reception": "2026-06-14",
      "peremption": "2028-06-14",
      "ouverture": "",
      "validite": "",
      "statut": "en_stock",
      "note": "",
      "id": 1781449960249
    },
    {
      "produitId": 1781446866469,
      "lot": "VBCN32443",
      "qte": "2.5 L",
      "reception": "2026-06-14",
      "peremption": "2028-06-14",
      "ouverture": "",
      "validite": "",
      "statut": "en_stock",
      "note": "",
      "id": 1781449960250
    },
    {
      "produitId": 1781446866469,
      "lot": "VBCN32443",
      "qte": "2.5 L",
      "reception": "2026-06-14",
      "peremption": "2028-06-14",
      "ouverture": "",
      "validite": "",
      "statut": "en_stock",
      "note": "",
      "id": 1781449960251
    },
    {
      "produitId": 1781446866469,
      "lot": "VBCN32443",
      "qte": "2.5 L",
      "reception": "2026-06-14",
      "peremption": "2028-06-14",
      "ouverture": "",
      "validite": "",
      "statut": "en_stock",
      "note": "",
      "id": 1781449960252
    },
    {
      "produitId": 1781446866469,
      "lot": "VBCN32443",
      "qte": "2.5 L",
      "reception": "2026-06-14",
      "peremption": "2028-06-14",
      "ouverture": "",
      "validite": "",
      "statut": "en_stock",
      "note": "",
      "id": 1781449960253
    },
    {
      "produitId": 1781446866469,
      "lot": "VBCN32443",
      "qte": "2.5 L",
      "reception": "2026-06-14",
      "peremption": "2028-06-14",
      "ouverture": "",
      "validite": "",
      "statut": "en_stock",
      "note": "",
      "id": 1781449960254
    },
    {
      "produitId": 1781446866469,
      "lot": "VBCN32443",
      "qte": "2.5 L",
      "reception": "2026-06-14",
      "peremption": "2028-06-14",
      "ouverture": "",
      "validite": "",
      "statut": "en_stock",
      "note": "",
      "id": 1781449960255
    },
    {
      "produitId": 1781446866469,
      "lot": "VBCN32443",
      "qte": "2.5 L",
      "reception": "2026-06-14",
      "peremption": "2028-06-14",
      "ouverture": "",
      "validite": "",
      "statut": "en_stock",
      "note": "",
      "id": 1781449960256
    },
    {
      "produitId": 1781446866469,
      "lot": "VBCN32443",
      "qte": "2.5 L",
      "reception": "2026-06-14",
      "peremption": "2028-06-14",
      "ouverture": "",
      "validite": "",
      "statut": "en_stock",
      "note": "",
      "id": 1781449960257
    }
  ],
  "produitsEch": [
    {
      "id": 1781508169429,
      "nom": "Xylocaïne 5% Naphazoline",
      "forme": "",
      "dosage": "",
      "code": "Na5",
      "responsable": "",
      "description": ""
    },
    {
      "id": 1781509248907,
      "nom": "Xylocaïne Nébuliseur",
      "forme": "",
      "dosage": "",
      "code": "Ne",
      "responsable": "",
      "description": ""
    },
    {
      "id": 1781509266740,
      "nom": "Lipiodol",
      "forme": "",
      "dosage": "",
      "code": "LIP",
      "responsable": "",
      "description": ""
    },
    {
      "id": 1781852369953,
      "nom": "Setmelanotide 10 mg/mL",
      "forme": "",
      "dosage": "10 mg/mL",
      "code": "SET",
      "responsable": "",
      "description": ""
    }
  ],
  "marches": [
    {
      "id": 1781508724125,
      "nom": "France",
      "code": "FR",
      "analyses": [],
      "note": ""
    },
    {
      "id": 1781509571572,
      "nom": "Canada",
      "code": "CA",
      "analyses": [],
      "note": ""
    },
    {
      "id": 1781853985902,
      "nom": "USA",
      "code": "US",
      "analyses": [],
      "note": ""
    },
    {
      "id": 1781959829280,
      "nom": "Global",
      "code": "G",
      "analyses": [],
      "note": ""
    }
  ],
  "echantillons": [
    {
      "id": 1781510120638,
      "code": "9960000-A",
      "produitId": 1781508169429,
      "marcheIds": [
        1781508724125
      ],
      "analysesIds": [
        1781508652926,
        1781509335357
      ],
      "typePIF": true,
      "typeSTAB": false,
      "stabEcheance": "",
      "stabTemps": "",
      "lot": "9960000",
      "date": "2026-06-15",
      "statut": "approuve",
      "note": "",
      "analyseStatuts": {
        "1781508652926": "verifiee",
        "1781509335357": "verifiee"
      },
      "analyseStatutsInfo": {
        "1781508652926": {
          "verifiee": "15/06/2026",
          "a_lancer": "15/06/26",
          "en_cours": "15/06/2026",
          "terminee": "15/06/2026"
        },
        "1781509335357": {
          "en_cours": "20/06/2026",
          "terminee": "20/06/2026",
          "verifiee": "20/06/2026"
        }
      },
      "dateApprobation": "20/06/2026"
    },
    {
      "id": 1781511540450,
      "code": "9960001-A",
      "produitId": 1781508169429,
      "marcheIds": [
        1781508724125
      ],
      "analysesIds": [
        1781508652926,
        1781509335357
      ],
      "typePIF": true,
      "typeSTAB": true,
      "stabEcheance": "",
      "stabTemps": "",
      "lot": "9960001",
      "date": "2026-06-15",
      "statut": "approuve",
      "note": "",
      "analyseStatuts": {
        "1781508652926": "verifiee",
        "1781509335357": "verifiee"
      },
      "analyseStatutsInfo": {
        "1781508652926": {
          "en_cours": "15/06/2026",
          "terminee": "15/06/2026",
          "verifiee": "15/06/2026"
        },
        "1781509335357": {
          "en_cours": "20/06/2026",
          "terminee": "20/06/2026",
          "verifiee": "20/06/2026"
        }
      },
      "dateApprobation": "20/06/2026"
    },
    {
      "id": 1781512857183,
      "code": "9960002-A",
      "produitId": 1781509248907,
      "marcheIds": [
        1781508724125,
        1781509571572
      ],
      "analysesIds": [
        1781509335357
      ],
      "typePIF": false,
      "typeSTAB": true,
      "stabEcheance": "",
      "stabTemps": "5C",
      "lot": "9960002",
      "date": "2026-06-15",
      "statut": "approuve",
      "note": "",
      "analyseStatuts": {
        "1781509335357": "verifiee"
      },
      "analyseStatutsInfo": {
        "1781509335357": {
          "en_cours": "20/06/2026",
          "terminee": "20/06/2026",
          "verifiee": "20/06/2026"
        }
      },
      "dateApprobation": "20/06/2026"
    },
    {
      "id": 1781602519100,
      "code": "9960003-A",
      "produitId": 1781508169429,
      "marcheIds": [
        1781508724125
      ],
      "analysesIds": [
        1781508652926,
        1781509335357
      ],
      "typePIF": true,
      "typeSTAB": true,
      "stabEcheance": "",
      "stabTemps": "",
      "lot": "9960003",
      "date": "2026-06-16",
      "statut": "recu",
      "note": ""
    },
    {
      "id": 1781602519101,
      "code": "9960003-B",
      "produitId": 1781508169429,
      "marcheIds": [
        1781508724125
      ],
      "analysesIds": [
        1781508652926,
        1781509335357
      ],
      "typePIF": true,
      "typeSTAB": true,
      "stabEcheance": "",
      "stabTemps": "",
      "lot": "9960003",
      "date": "2026-06-16",
      "statut": "recu",
      "note": ""
    },
    {
      "id": 1781602519102,
      "code": "9960003-C",
      "produitId": 1781508169429,
      "marcheIds": [
        1781508724125
      ],
      "analysesIds": [
        1781508652926,
        1781509335357
      ],
      "typePIF": true,
      "typeSTAB": true,
      "stabEcheance": "",
      "stabTemps": "",
      "lot": "9960003",
      "date": "2026-06-16",
      "statut": "recu",
      "note": ""
    },
    {
      "id": 1781853049925,
      "code": "AAAAAAA-A",
      "produitId": 1781852369953,
      "marcheIds": [
        1781509571572
      ],
      "analysesIds": [
        1781852405020,
        1781852438719,
        1781852984224
      ],
      "typePIF": true,
      "typeSTAB": false,
      "stabEcheance": "",
      "stabTemps": "",
      "lot": "AAAAAAA",
      "date": "2026-06-19",
      "statut": "en_analyse",
      "note": "",
      "analyseStatuts": {
        "1781852438719": "terminee"
      },
      "analyseStatutsInfo": {
        "1781852438719": {
          "en_cours": "19/06/2026",
          "terminee": "20/06/2026"
        }
      }
    },
    {
      "id": 1781960722999,
      "code": "BBBBBB-A",
      "produitId": 1781852369953,
      "marcheIds": [
        1781853985902
      ],
      "analysesIds": [
        1781509335357,
        1781852405020,
        1781852438719,
        1781852984224,
        1781959632897,
        1781959743113
      ],
      "typePIF": true,
      "typeSTAB": false,
      "stabEcheance": "",
      "stabTemps": "",
      "lot": "BBBBBB",
      "date": "2026-06-20",
      "statut": "recu",
      "note": ""
    }
  ],
  "techniciens": [
    {
      "id": 1781508237179,
      "prenom": "Fabien",
      "nom": "VARY",
      "role": "Technicien CQ",
      "habilitations": [
        "HPLC",
        "Balance",
        "pH"
      ],
      "date": "2021-11-20",
      "statut": "actif"
    }
  ],
  "commandesStatut": {
    "1781446866469": "en_attente"
  },
  "enregistrements": [],
  "activity": [
    {
      "icon": "list-check",
      "text": "9960000-A — TCC0015 : verifiee",
      "time": "15/06 10:26"
    },
    {
      "icon": "list-check",
      "text": "9960000-A — TCC0015 : a_lancer",
      "time": "15/06 10:26"
    },
    {
      "icon": "list-check",
      "text": "9960000-A — TCC0015 : en_cours",
      "time": "15/06 10:26"
    },
    {
      "icon": "list-check",
      "text": "9960000-A — TCC0015 : terminee",
      "time": "15/06 10:26"
    },
    {
      "icon": "list-check",
      "text": "9960000-A — TCC0015 : verifiee",
      "time": "15/06 10:26"
    },
    {
      "icon": "list-check",
      "text": "9960000-A — TCC0015 : a_lancer",
      "time": "15/06 10:26"
    },
    {
      "icon": "list-check",
      "text": "9960000-A — TCC0015 : en_cours",
      "time": "15/06 10:27"
    },
    {
      "icon": "list-check",
      "text": "9960000-A — TCC0015 : terminee",
      "time": "15/06 10:27"
    },
    {
      "icon": "list-check",
      "text": "9960000-A — TCC0015 : verifiee",
      "time": "15/06 10:27"
    },
    {
      "icon": "list-check",
      "text": "9960000-A — TCC0015 : a_lancer",
      "time": "15/06 10:27"
    },
    {
      "icon": "list-check",
      "text": "9960000-A — TCC0015 : en_cours",
      "time": "15/06 10:39"
    },
    {
      "icon": "list-check",
      "text": "9960000-A — TCC0015 : terminee",
      "time": "15/06 10:39"
    },
    {
      "icon": "list-check",
      "text": "9960000-A — TCC0015 : verifiee",
      "time": "15/06 10:39"
    },
    {
      "icon": "list-check",
      "text": "9960001-A — TCC0015 : en_cours",
      "time": "15/06 10:39"
    },
    {
      "icon": "list-check",
      "text": "9960001-A — TCC0015 : terminee",
      "time": "15/06 10:39"
    },
    {
      "icon": "list-check",
      "text": "9960001-A — TCC0015 : verifiee",
      "time": "15/06 10:39"
    },
    {
      "icon": "package",
      "text": "Reception: Xylocaïne Nébuliseur — 1 sous-serie — 1 analyse",
      "time": "15/06 10:40"
    },
    {
      "icon": "package",
      "text": "Reception: Xylocaïne 5% Naphazoline — 3 sous-series — 2 analyses",
      "time": "16/06 11:35"
    },
    {
      "icon": "pill",
      "text": "Produit ajoute : Setmelanotide 10 mg/mL",
      "time": "19/06 08:59"
    },
    {
      "icon": "book",
      "text": "Analyse ajoutee au catalogue : L*a*b",
      "time": "19/06 09:00"
    },
    {
      "icon": "book",
      "text": "Analyse ajoutee au catalogue : TCC0044",
      "time": "19/06 09:00"
    },
    {
      "icon": "book",
      "text": "Analyse ajoutee au catalogue : Osmolalité",
      "time": "19/06 09:09"
    },
    {
      "icon": "package",
      "text": "Reception: Setmelanotide 10 mg/mL — 1 sous-serie — 3 analyses",
      "time": "19/06 09:10"
    },
    {
      "icon": "book",
      "text": "Analyse modifiee : TCC0015",
      "time": "19/06 09:12"
    },
    {
      "icon": "book",
      "text": "Analyse modifiee : TCC0015 (Phase Mobile)",
      "time": "19/06 09:12"
    },
    {
      "icon": "book",
      "text": "Analyse modifiee : pH",
      "time": "19/06 09:12"
    },
    {
      "icon": "list-check",
      "text": "AAAAAAA-A — TCC0044 : en_cours",
      "time": "19/06 09:18"
    },
    {
      "icon": "world",
      "text": "Marche ajoute : USA",
      "time": "19/06 09:26"
    },
    {
      "icon": "list-check",
      "text": "9960002-A — pH : en_cours",
      "time": "20/06 12:51"
    },
    {
      "icon": "list-check",
      "text": "9960002-A — pH : terminee",
      "time": "20/06 12:57"
    },
    {
      "icon": "list-check",
      "text": "9960002-A — pH : verifiee",
      "time": "20/06 12:57"
    },
    {
      "icon": "list-check",
      "text": "9960001-A — pH : en_cours",
      "time": "20/06 12:57"
    },
    {
      "icon": "list-check",
      "text": "9960001-A — pH : terminee",
      "time": "20/06 12:57"
    },
    {
      "icon": "list-check",
      "text": "9960001-A — pH : verifiee",
      "time": "20/06 12:57"
    },
    {
      "icon": "list-check",
      "text": "9960000-A — pH : en_cours",
      "time": "20/06 12:58"
    },
    {
      "icon": "list-check",
      "text": "9960000-A — pH : terminee",
      "time": "20/06 13:03"
    },
    {
      "icon": "rosette",
      "text": "Lot libere : 9960001 (Xylocaïne 5% Naphazoline)",
      "time": "20/06 13:09"
    },
    {
      "icon": "rosette",
      "text": "Lot libere : 9960001 (Xylocaïne 5% Naphazoline)",
      "time": "20/06 13:09"
    },
    {
      "icon": "rosette",
      "text": "Lot libere : 9960001 (Xylocaïne 5% Naphazoline)",
      "time": "20/06 13:09"
    },
    {
      "icon": "rosette",
      "text": "Lot libere : 9960002 (Xylocaïne Nébuliseur)",
      "time": "20/06 13:09"
    },
    {
      "icon": "rosette",
      "text": "Lot libere : 9960002 (Xylocaïne Nébuliseur)",
      "time": "20/06 13:09"
    },
    {
      "icon": "rosette",
      "text": "Lot libere : 9960002 (Xylocaïne Nébuliseur)",
      "time": "20/06 13:09"
    },
    {
      "icon": "list-check",
      "text": "9960000-A — pH : verifiee",
      "time": "20/06 13:15"
    },
    {
      "icon": "list-check",
      "text": "AAAAAAA-A — TCC0044 : terminee",
      "time": "20/06 13:15"
    },
    {
      "icon": "book",
      "text": "Analyse ajoutee au catalogue : TCC0065",
      "time": "20/06 14:47"
    },
    {
      "icon": "book",
      "text": "Analyse modifiee : TCC0044",
      "time": "20/06 14:48"
    },
    {
      "icon": "book",
      "text": "Analyse ajoutee au catalogue : Volume Extractible",
      "time": "20/06 14:49"
    },
    {
      "icon": "world",
      "text": "Marche ajoute : Global",
      "time": "20/06 14:50"
    },
    {
      "icon": "package",
      "text": "Reception: Setmelanotide 10 mg/mL — 1 sous-serie — 6 analyses",
      "time": "20/06 15:05"
    },
    {
      "icon": "rosette",
      "text": "Lot libere : 9960000 (Xylocaïne 5% Naphazoline)",
      "time": "20/06 15:10"
    }
  ]
}